.gitignore
MANIFEST.in
README.txt
medialog.maritheme-configure.zcml
setup.cfg
setup.py
docs/HISTORY.txt
docs/INSTALL.txt
docs/LICENSE.GPL
docs/LICENSE.txt
medialog/.DS_Store
medialog/__init__.py
medialog.maritheme.egg-info/PKG-INFO
medialog.maritheme.egg-info/SOURCES (G-Ms-iMac's conflicted copy 2013-03-16).txt
medialog.maritheme.egg-info/SOURCES.txt
medialog.maritheme.egg-info/dependency_links.txt
medialog.maritheme.egg-info/entry_points.txt
medialog.maritheme.egg-info/namespace_packages.txt
medialog.maritheme.egg-info/not-zip-safe
medialog.maritheme.egg-info/paster_plugins.txt
medialog.maritheme.egg-info/requires.txt
medialog.maritheme.egg-info/top_level.txt
medialog/maritheme/.DS_Store
medialog/maritheme/__init__.py
medialog/maritheme/configure.zcml
medialog/maritheme/profiles.zcml
medialog/maritheme/setuphandlers.py
medialog/maritheme/skins.zcml
medialog/maritheme/tests.py
medialog/maritheme/version.txt
medialog/maritheme/browser/.DS_Store
medialog/maritheme/browser/__init__.py
medialog/maritheme/browser/configure.zcml
medialog/maritheme/browser/interfaces.py
medialog/maritheme/browser/managetopportlets.pt
medialog/maritheme/browser/maritheme_banner.pt
medialog/maritheme/browser/maritheme_colophon.pt
medialog/maritheme/browser/maritheme_siteactions.pt
medialog/maritheme/browser/topportlets.pt
medialog/maritheme/browser/viewlets.py
medialog/maritheme/browser/views.py
medialog/maritheme/browser/images/README.txt
medialog/maritheme/browser/stylesheets/README.txt
medialog/maritheme/locales/README.txt
medialog/maritheme/profiles/.DS_Store
medialog/maritheme/profiles/default/.DS_Store
medialog/maritheme/profiles/default/actions.xml
medialog/maritheme/profiles/default/cssregistry.xml
medialog/maritheme/profiles/default/jsregistry.xml
medialog/maritheme/profiles/default/medialog.maritheme_various.txt
medialog/maritheme/profiles/default/metadata.xml
medialog/maritheme/profiles/default/portlets.xml
medialog/maritheme/profiles/default/propertiestool.xml
medialog/maritheme/profiles/default/skins.xml
medialog/maritheme/profiles/default/viewlets.xml
medialog/maritheme/skins/.DS_Store
medialog/maritheme/skins/medialog_maritheme_custom_images/.DS_Store
medialog/maritheme/skins/medialog_maritheme_custom_images/000forlopvII.jpg
medialog/maritheme/skins/medialog_maritheme_custom_images/Email.png
medialog/maritheme/skins/medialog_maritheme_custom_images/Featureclose.png
medialog/maritheme/skins/medialog_maritheme_custom_images/RSS.png
