Metadata-Version: 1.0
Name: medialog.maritheme
Version: 0.1.3
Summary: Medialog Maritheme
Home-page: https://github.com/espenmn/medialog.maritheme/
Author: EMN
Author-email: espen@medialog.no
License: GPL
Keywords: Plone Theme Maritheme
Platform: UNKNOWN
Classifier: Framework :: Plone
Classifier: Programming Language :: Python
